toppred/__init__.py
toppred/metrics.py
toppred/predictions.py
toppred/types.py
toppred/utils.py
toppred-0.0.3.dist-info/LICENSE
toppred-0.0.3.dist-info/METADATA
toppred-0.0.3.dist-info/WHEEL
toppred-0.0.3.dist-info/top_level.txt
toppred-0.0.3.dist-info/RECORD
