Metadata-Version: 2.1
Name: toppred
Version: 0.0.3
Summary: Extension to sklearn.metrics to allow metrics with multiple predictions. 
Author-email: Thijs van Ede <t.s.vanede@utwente.nl>
License: MIT License
Project-URL: Homepage, https://github.com/Thijsvanede/toppred
Project-URL: Bug Tracker, https://github.com/Thijsvanede/toppred/issues
Classifier: Programming Language :: Python :: 3
Classifier: License :: OSI Approved :: MIT License
Classifier: Operating System :: OS Independent
Requires-Python: >=3.8
License-File: LICENSE
